openapi_markdown/__init__.py
openapi_markdown/generator.py
openapi_markdown/bin/__init__.py
openapi_markdown/bin/cli.py
openapi_markdown/templates/_content.md.j2
openapi_markdown/templates/_example.md.j2
openapi_markdown/templates/_object_schema.md.j2
openapi_markdown/templates/_security_scheme.md.j2
openapi_markdown/templates/api_doc_template.md.j2
openapi_markdown/templates/embed/_content.md.j2
openapi_markdown/templates/embed/_example.md.j2
openapi_markdown/templates/embed/_object_schema.md.j2
openapi_markdown/templates/embed/_security_scheme.md.j2
openapi_markdown/templates/embed/api_doc_template.md.j2
openapi_markdown-0.4.3.dist-info/METADATA
openapi_markdown-0.4.3.dist-info/WHEEL
openapi_markdown-0.4.3.dist-info/entry_points.txt
openapi_markdown-0.4.3.dist-info/licenses/LICENSE
openapi_markdown-0.4.3.dist-info/RECORD
