Metadata-Version: 2.4
Name: openapi-markdown
Version: 0.4.3
Summary: Generates API documentation from an OpenAPI specification file
Project-URL: Homepage, https://github.com/vrerv/openapi-markdown
Project-URL: Bug Tracker, https://github.com/vrerv/openapi-markdown/issues
Author-email: soonoh <soonoh.jung@vrerv.com>
License-File: LICENSE
Classifier: Intended Audience :: Developers
Classifier: Intended Audience :: Information Technology
Classifier: Programming Language :: Python
Classifier: Programming Language :: Python :: 3 :: Only
Requires-Python: >=3.7
Requires-Dist: click==8.1.*
Requires-Dist: jinja2==3.1.*
Requires-Dist: openapi-core==0.19.*
Requires-Dist: pyyaml==6.0.2
